<?xml version="1.0" encoding="ASCII"?>
<!DOCTYPE nm:output SYSTEM "output.dtd">
<nm:output
xmlns:xsi="http://www.w3.org/2001/XMLSchema-instance"
xsi:schemaLocation="http://namespaces.oreilly.com/xmlnut/address output.xsd"
xmlns:nm="http://namespaces.oreilly.com/xmlnut/address"
>
<nm:start_datetime>2023-11-24T16:45:28.858</nm:start_datetime>
<nm:control_stream><![CDATA[
$PROBLEM From bbr: see 1000-FOCE.yaml for details

$INPUT C NUM ID TIME SEQ CMT EVID AMT DV AGE WT HT EGFR ALB BMI SEX AAG
  SCR AST ALT CP TAFD TAD LDOS MDV BLQ PHASE

$DATA ../../../data/derived/analysis3.csv IGNORE=(C='C', BLQ=1)

$SUBROUTINE ADVAN4 TRANS4

$PK

;log transformed PK parms

  V2WT   = LOG(WT/70)
  CLWT   = LOG(WT/70) * 0.75
  V3WT   = LOG(WT/70)
  QWT    = LOG(WT/70) * 0.75

  MU_1   = THETA(1)
  MU_2   = THETA(2) + V2WT
  MU_3   = THETA(3) + CLWT
  MU_4   = THETA(4) + V3WT
  MU_5   = THETA(5) + QWT

  KA     = EXP(MU_1 + ETA(1))
  V2     = EXP(MU_2 + ETA(2))
  CL     = EXP(MU_3 + ETA(3))
  V3     = EXP(MU_4 + ETA(4))
  Q      = EXP(MU_5 + ETA(5))

  S2     = V2/1000 ; dose in mcg, conc in mcg/mL

$ERROR

  IPRED = F
  Y     = IPRED * (1 + EPS(1))

$THETA  ; log values
  (0.5)   ;  1 KA (1/hr) - 1.5
  (3.5)   ;  2 V2 (L) - 60
  (1)     ;  3 CL (L/hr) - 3.5
  (4)     ;  4 V3 (L) - 70
  (2)     ;  5 Q  (L/hr) - 4

$OMEGA BLOCK(3)
  0.2   ;ETA(KA)
  0.01 0.2   ;ETA(V2)
  0.01 0.01 0.2   ;ETA(CL)

$OMEGA
  0 FIX    ; ETA(V3)
  0 FIX    ; ETA(Q)

$SIGMA
  0.05     ; 1 pro error

$EST MAXEVAL=9999 METHOD=1 INTER SIGL=6 NSIG=3 PRINT=1 MSFO=./1000-FOCE.msf
$COV PRINT=E
$TABLE NUM CL V2 Q V3 KA ETAS(1:LAST) IPRED NPDE CWRES NOPRINT ONEHEADER FILE=1000-FOCE.tab
]]></nm:control_stream>
<nm:nmtran><![CDATA[

 WARNINGS AND ERRORS (IF ANY) FOR PROBLEM    1

 (WARNING  2) NM-TRAN INFERS THAT THE DATA ARE POPULATION.

 (MU_WARNING 26) DATA ITEM(S) USED IN DEFINITION OF MU_(S) SHOULD BE CONSTANT FOR INDIV. REC.:
  WT

 LIM VALUES MAXLIM ASSESSED BY NMTRAN: 1,2,3,4,5,6,7,8,10,11,13,15,16

Note: Analytical 2nd Derivatives are constructed in FSUBS but are never used.
      You may insert $ABBR DERIV2=NO after the first $PROB to save FSUBS construction and compilation time

]]></nm:nmtran>
<nm:nonmem nm:version='7.5.1'>
<nm:license_information><![CDATA[
License Registered to: Metrum Research Group
Expiration Date:    14 JUL 2024
Current Date:       24 NOV 2023
Days until program expires : 235
]]></nm:license_information>
<nm:program_information><![CDATA[
1NONLINEAR MIXED EFFECTS MODEL PROGRAM (NONMEM) VERSION 7.5.1
 ORIGINALLY DEVELOPED BY STUART BEAL, LEWIS SHEINER, AND ALISON BOECKMANN
 CURRENT DEVELOPERS ARE ROBERT BAUER, ICON DEVELOPMENT SOLUTIONS,
 AND ALISON BOECKMANN. IMPLEMENTATION, EFFICIENCY, AND STANDARDIZATION
 PERFORMED BY NOUS INFOSYSTEMS.
]]></nm:program_information>
<nm:problem nm:number='1' nm:subproblem='0' nm:superproblem1='0' nm:iteration1='0' nm:superproblem2='0' nm:iteration2='0'>
<nm:problem_title>From bbr: see 1000-FOCE.yaml for details</nm:problem_title>
<nm:problem_information><![CDATA[

 PROBLEM NO.:         1
 From bbr: see 1000-FOCE.yaml for details
0DATA CHECKOUT RUN:              NO
 DATA SET LOCATED ON UNIT NO.:    2
 THIS UNIT TO BE REWOUND:        NO
 NO. OF DATA RECS IN DATA SET:     4292
 NO. OF DATA ITEMS IN DATA SET:  27
 ID DATA ITEM IS DATA ITEM NO.:   3
 DEP VARIABLE IS DATA ITEM NO.:   9
 MDV DATA ITEM IS DATA ITEM NO.: 25
0INDICES PASSED TO SUBROUTINE PRED:
   7   4   8   0   0   0   6   0   0   0   0
0LABELS FOR DATA ITEMS:
 C NUM ID TIME SEQ CMT EVID AMT DV AGE WT HT EGFR ALB BMI SEX AAG SCR AST ALT CP TAFD TAD LDOS MDV BLQ PHASE
0(NONBLANK) LABELS FOR PRED-DEFINED ITEMS:
 KA V2 CL V3 Q IPRED
0FORMAT FOR DATA:
 (2(10E7.0/),7E7.0)

 TOT. NO. OF OBS RECS:     3142
 TOT. NO. OF INDIVIDUALS:      160
0LENGTH OF THETA:   5
0DEFAULT THETA BOUNDARY TEST OMITTED:    NO
0OMEGA HAS BLOCK FORM:
  1
  1  1
  1  1  1
  0  0  0  2
  0  0  0  0  3
0DEFAULT OMEGA BOUNDARY TEST OMITTED:    NO
0SIGMA HAS SIMPLE DIAGONAL FORM WITH DIMENSION:   1
0DEFAULT SIGMA BOUNDARY TEST OMITTED:    NO
0INITIAL ESTIMATE OF THETA:
   0.5000E+00  0.3500E+01  0.1000E+01  0.4000E+01  0.2000E+01
0INITIAL ESTIMATE OF OMEGA:
 BLOCK SET NO.   BLOCK                                                                    FIXED
        1                                                                                   NO
                  0.2000E+00
                  0.1000E-01   0.2000E+00
                  0.1000E-01   0.1000E-01   0.2000E+00
        2                                                                                  YES
                  0.0000E+00
        3                                                                                  YES
                  0.0000E+00
0INITIAL ESTIMATE OF SIGMA:
 0.5000E-01
0COVARIANCE STEP OMITTED:        NO
 EIGENVLS. PRINTED:             YES
 SPECIAL COMPUTATION:            NO
 COMPRESSED FORMAT:              NO
 GRADIENT METHOD USED:     NOSLOW
 SIGDIGITS ETAHAT (SIGLO):                  -1
 SIGDIGITS GRADIENTS (SIGL):                -1
 EXCLUDE COV FOR FOCE (NOFCOV):              NO
 Cholesky Transposition of R Matrix (CHOLROFF):0
 KNUTHSUMOFF:                                -1
 RESUME COV ANALYSIS (RESUME):               NO
 SIR SAMPLE SIZE (SIRSAMPLE):
 NON-LINEARLY TRANSFORM THETAS DURING COV (THBND): 1
 PRECONDTIONING CYCLES (PRECOND):        0
 PRECONDTIONING TYPES (PRECONDS):        TOS
 FORCED PRECONDTIONING CYCLES (PFCOND):0
 PRECONDTIONING TYPE (PRETYPE):        0
 FORCED POS. DEFINITE SETTING DURING PRECONDITIONING: (FPOSDEF):0
 SIMPLE POS. DEFINITE SETTING: (POSDEF):-1
0TABLES STEP OMITTED:    NO
 NO. OF TABLES:           1
 SEED NUMBER (SEED):    11456
 NPDTYPE:    0
 INTERPTYPE:    0
 RANMETHOD:             3U
 MC SAMPLES (ESAMPLE):    300
 WRES SQUARE ROOT TYPE (WRESCHOL): EIGENVALUE
0-- TABLE   1 --
0RECORDS ONLY:    ALL
04 COLUMNS APPENDED:    YES
 PRINTED:                NO
 HEADERS:               ONE
 FILE TO BE FORWARDED:   NO
 FORMAT:                S1PE11.4
 IDFORMAT:
 LFORMAT:
 RFORMAT:
 FIXED_EFFECT_ETAS:
0USER-CHOSEN ITEMS:
 NUM CL V2 Q V3 KA ETA1 ETA2 ETA3 ETA4 ETA5 IPRED NPDE CWRES
1DOUBLE PRECISION PREDPP VERSION 7.5.1

 TWO COMPARTMENT MODEL WITH FIRST-ORDER ABSORPTION (ADVAN4)
0MAXIMUM NO. OF BASIC PK PARAMETERS:   5
0BASIC PK PARAMETERS (AFTER TRANSLATION):
   BASIC PK PARAMETER NO.  1: ELIMINATION RATE (K)
   BASIC PK PARAMETER NO.  2: CENTRAL-TO-PERIPH. RATE (K23)
   BASIC PK PARAMETER NO.  3: PERIPH.-TO-CENTRAL RATE (K32)
   BASIC PK PARAMETER NO.  5: ABSORPTION RATE (KA)
 TRANSLATOR WILL CONVERT PARAMETERS
 CL, V2, Q, V3 TO K, K23, K32 (TRANS4)
0COMPARTMENT ATTRIBUTES
 COMPT. NO.   FUNCTION   INITIAL    ON/OFF      DOSE      DEFAULT    DEFAULT
                         STATUS     ALLOWED    ALLOWED    FOR DOSE   FOR OBS.
    1         DEPOT        OFF        YES        YES        YES        NO
    2         CENTRAL      ON         NO         YES        NO         YES
    3         PERIPH.      ON         NO         YES        NO         NO
    4         OUTPUT       OFF        YES        NO         NO         NO
1
 ADDITIONAL PK PARAMETERS - ASSIGNMENT OF ROWS IN GG
 COMPT. NO.                             INDICES
              SCALE      BIOAVAIL.   ZERO-ORDER  ZERO-ORDER  ABSORB
                         FRACTION    RATE        DURATION    LAG
    1            *           *           *           *           *
    2            6           *           *           *           *
    3            *           *           *           *           *
    4            *           -           -           -           -
             - PARAMETER IS NOT ALLOWED FOR THIS MODEL
             * PARAMETER IS NOT SUPPLIED BY PK SUBROUTINE;
               WILL DEFAULT TO ONE IF APPLICABLE
0DATA ITEM INDICES USED BY PRED ARE:
   EVENT ID DATA ITEM IS DATA ITEM NO.:      7
   TIME DATA ITEM IS DATA ITEM NO.:          4
   DOSE AMOUNT DATA ITEM IS DATA ITEM NO.:   8
   COMPT. NO. DATA ITEM IS DATA ITEM NO.:    6

0PK SUBROUTINE CALLED WITH EVERY EVENT RECORD.
 PK SUBROUTINE NOT CALLED AT NONEVENT (ADDITIONAL OR LAGGED) DOSE TIMES.
0ERROR SUBROUTINE CALLED WITH EVERY EVENT RECORD.
]]></nm:problem_information>
<nm:problem_options
 nm:data_checkout_run='no' nm:data_unit='2' nm:data_rewind='no' nm:data_nrec='4292' nm:data_nitems='27' nm:data_id='3'
 nm:data_l2='0' nm:data_dv='9' nm:data_mdv='25' nm:data_mrg='0' nm:data_raw='0' nm:data_rpt='0' nm:data_sub_array1='0'
 nm:data_sub_array2='0' nm:data_sub_array3='0' nm:data_pred_indices='7,4,8,0,0,0,6,0,0,0,0'
 nm:data_format='(2(10e7.0/),7e7.0)' nm:data_nobs='3142' nm:data_nind='160' nm:data_mdv100='0' nm:nthetat='5'
 nm:theta_bound_test_omitted='no' nm:omega_blockdim='5' nm:omega_bound_test_omitted='no' nm:sigma_diagdim='1'
 nm:sigma_bound_test_omitted='no' nm:cov_omitted='no' nm:cov_matrix='rsr' nm:cov_eigen_print='yes'
 nm:cov_special='no' nm:cov_compressed='no' nm:cov_slow_gradient='noslow' nm:cov_siglocov='-1' nm:cov_siglcov='-1'
 nm:cov_tol='-1' nm:cov_atol='-1' nm:cov_nofcov='no' nm:cov_cholroff='0' nm:cov_knuthsumoff='-1' nm:cov_resume='no'
 nm:cov_sirsample='BLANK' nm:cov_thbnd='1' nm:cov_precond='0' nm:cov_preconds='tos' nm:cov_pfcond='0'
 nm:cov_pretype='0' nm:cov_fposdef='0' nm:cov_posdef='-1' nm:tab_omitted='no' nm:tab_number='1' nm:tab_seed='11456'
 nm:tab_npdtype='0' nm:tab_interptype='0' nm:tab_ranmethod='3u' nm:tab_esample='300' nm:tab_wres='eigenvalue'
 nm:tab_fixedetas_01='BLANK' nm:pred_advan='4' nm:pred_evid='7' nm:pred_time='4' nm:pred_amt='8' nm:pred_cmt='6'
/>
<nm:estimation nm:number='1' nm:type='0'>
<nm:table_series>1</nm:table_series>
<nm:estimation_method>focei</nm:estimation_method>
<nm:estimation_title>First Order Conditional Estimation with Interaction</nm:estimation_title>
<nm:estimation_information><![CDATA[
 ESTIMATION STEP OMITTED:                 NO
 ANALYSIS TYPE:                           POPULATION
 NUMBER OF SADDLE POINT RESET ITERATIONS:      0
 GRADIENT METHOD USED:               NOSLOW
 CONDITIONAL ESTIMATES USED:              YES
 CENTERED ETA:                            NO
 EPS-ETA INTERACTION:                     YES
 LAPLACIAN OBJ. FUNC.:                    NO
 NO. OF FUNCT. EVALS. ALLOWED:            9999
 NO. OF SIG. FIGURES REQUIRED:            3
 INTERMEDIATE PRINTOUT:                   YES
 ESTIMATE OUTPUT TO MSF:                  YES
 IND. OBJ. FUNC. VALUES SORTED:           NO
 NUMERICAL DERIVATIVE
       FILE REQUEST (NUMDER):               NONE
 MAP (ETAHAT) ESTIMATION METHOD (OPTMAP):   0
 ETA HESSIAN EVALUATION METHOD (ETADER):    0
 INITIAL ETA FOR MAP ESTIMATION (MCETA):    0
 SIGDIGITS FOR MAP ESTIMATION (SIGLO):      6
 GRADIENT SIGDIGITS OF
       FIXED EFFECTS PARAMETERS (SIGL):     6
 NOPRIOR SETTING (NOPRIOR):                 0
 NOCOV SETTING (NOCOV):                     OFF
 DERCONT SETTING (DERCONT):                 OFF
 FINAL ETA RE-EVALUATION (FNLETA):          1
 EXCLUDE NON-INFLUENTIAL (NON-INFL.) ETAS
       IN SHRINKAGE (ETASTYPE):             NO
 NON-INFL. ETA CORRECTION (NONINFETA):      0
 RAW OUTPUT FILE (FILE): 1000-FOCE.ext
 EXCLUDE TITLE (NOTITLE):                   NO
 EXCLUDE COLUMN LABELS (NOLABEL):           NO
 FORMAT FOR ADDITIONAL FILES (FORMAT):      S1PE12.5
 PARAMETER ORDER FOR OUTPUTS (ORDER):       TSOL
 KNUTHSUMOFF:                               0
 INCLUDE LNTWOPI:                           NO
 INCLUDE CONSTANT TERM TO PRIOR (PRIORC):   NO
 INCLUDE CONSTANT TERM TO OMEGA (ETA) (OLNTWOPI):NO
 ADDITIONAL CONVERGENCE TEST (CTYPE=4)?:    NO
 EM OR BAYESIAN METHOD USED:                 NONE

]]></nm:estimation_information>
<nm:estimation_options
 nm:estim_omitted='no' nm:analysis_type='pop' nm:saddle_reset='0' nm:saddle_hess='0' nm:slow_gradient='noslow'
 nm:cond_estim='yes' nm:centered_eta='no' nm:epseta_interaction='yes' nm:laplace='no' nm:predflag='0' nm:maxfn='9999'
 nm:nsig='3' nm:msfo='yes' nm:objsort='no' nm:numder='0' nm:optmap='0' nm:etader='0' nm:mceta='0' nm:siglo='6' nm:sigl='6'
 nm:noprior='0' nm:nocov='0' nm:dercont='0' nm:atol='0' nm:fnleta='1' nm:etastype='0' nm:noninfeta='0'
 nm:file='1000-foce.ext' nm:notitle='0' nm:nolabel='0' nm:format='s1pe12.5' nm:order='tsol' nm:knuthsumoff='0'
 nm:lntwopi='0' nm:priorc='0' nm:olntwopi='0' nm:ctype='0'
/>
<nm:monitor>
<nm:obj nm:iteration='0'>31993.031115707257</nm:obj>
<nm:obj nm:iteration='1'>31737.860175407222</nm:obj>
<nm:obj nm:iteration='2'>31658.433901004177</nm:obj>
<nm:obj nm:iteration='3'>31312.068194673026</nm:obj>
<nm:obj nm:iteration='4'>31290.719901710807</nm:obj>
<nm:obj nm:iteration='5'>31278.084233118760</nm:obj>
<nm:obj nm:iteration='6'>31246.716344655211</nm:obj>
<nm:obj nm:iteration='7'>31234.310390821807</nm:obj>
<nm:obj nm:iteration='8'>31190.408490831840</nm:obj>
<nm:obj nm:iteration='9'>31179.999137376679</nm:obj>
<nm:obj nm:iteration='10'>31176.716131669087</nm:obj>
<nm:obj nm:iteration='11'>31168.263884228680</nm:obj>
<nm:obj nm:iteration='12'>31163.337735150679</nm:obj>
<nm:obj nm:iteration='13'>31072.477692376553</nm:obj>
<nm:obj nm:iteration='14'>31056.974019097855</nm:obj>
<nm:obj nm:iteration='15'>31017.545088663632</nm:obj>
<nm:obj nm:iteration='16'>31004.623362167942</nm:obj>
<nm:obj nm:iteration='17'>31003.653912673610</nm:obj>
<nm:obj nm:iteration='18'>31002.455071689576</nm:obj>
<nm:obj nm:iteration='19'>31002.443839491032</nm:obj>
<nm:obj nm:iteration='20'>31002.427978757074</nm:obj>
<nm:obj nm:iteration='21'>31002.416234705033</nm:obj>
<nm:obj nm:iteration='22'>31002.376378396377</nm:obj>
<nm:obj nm:iteration='23'>31002.376378396377</nm:obj>
<nm:obj nm:iteration='24'>30998.748024232304</nm:obj>
<nm:obj nm:iteration='25'>30997.950730995108</nm:obj>
<nm:obj nm:iteration='26'>30997.913793054191</nm:obj>
<nm:obj nm:iteration='27'>30997.908057129251</nm:obj>
<nm:obj nm:iteration='28'>30997.907860469291</nm:obj>
<nm:obj nm:iteration='29'>30997.907860469291</nm:obj>
</nm:monitor>
<nm:termination_status>0</nm:termination_status>
<nm:termination_nfuncevals>350</nm:termination_nfuncevals>
<nm:termination_sigdigits>3.0754661644787471</nm:termination_sigdigits>
<nm:termination_information><![CDATA[
0MINIMIZATION SUCCESSFUL
 NO. OF FUNCTION EVALUATIONS USED:      350
 NO. OF SIG. DIGITS IN FINAL EST.:  3.1
]]></nm:termination_information>
<nm:termination_txtmsg>
<nm:val nm:name='1'>37</nm:val>
</nm:termination_txtmsg>
<nm:etabar>
<nm:row nm:rname='SUBPOP1'>
<nm:col nm:cname='ETA1'>-1.8974600196030533E-002</nm:col>
<nm:col nm:cname='ETA2'>-2.8496611674650695E-003</nm:col>
<nm:col nm:cname='ETA3'>1.2811046052705339E-003</nm:col>
<nm:col nm:cname='ETA4'>0.0000000000000000</nm:col>
<nm:col nm:cname='ETA5'>0.0000000000000000</nm:col>
</nm:row>
</nm:etabar>
<nm:etabarse>
<nm:row nm:rname='SUBPOP1'>
<nm:col nm:cname='ETA1'>3.0390385871667744E-002</nm:col>
<nm:col nm:cname='ETA2'>2.1297637170449947E-002</nm:col>
<nm:col nm:cname='ETA3'>3.2219085658046411E-002</nm:col>
<nm:col nm:cname='ETA4'>0.0000000000000000</nm:col>
<nm:col nm:cname='ETA5'>0.0000000000000000</nm:col>
</nm:row>
</nm:etabarse>
<nm:etabarn>
<nm:row nm:rname='SUBPOP1'>
<nm:col nm:cname='ETA1'>160</nm:col>
<nm:col nm:cname='ETA2'>160</nm:col>
<nm:col nm:cname='ETA3'>160</nm:col>
<nm:col nm:cname='ETA4'>160</nm:col>
<nm:col nm:cname='ETA5'>160</nm:col>
</nm:row>
</nm:etabarn>
<nm:etabarpval>
<nm:row nm:rname='SUBPOP1'>
<nm:col nm:cname='ETA1'>0.53238979349764859</nm:col>
<nm:col nm:cname='ETA2'>0.89355927340120911</nm:col>
<nm:col nm:cname='ETA3'>0.96828251507856844</nm:col>
<nm:col nm:cname='ETA4'>1.0000000000000000</nm:col>
<nm:col nm:cname='ETA5'>1.0000000000000000</nm:col>
</nm:row>
</nm:etabarpval>
<nm:etashrinksd>
<nm:row nm:rname='SUBPOP1'>
<nm:col nm:cname='ETA1'>18.155805986826202</nm:col>
<nm:col nm:cname='ETA2'>6.3173579389181445</nm:col>
<nm:col nm:cname='ETA3'>0.89837117953298629</nm:col>
<nm:col nm:cname='ETA4'>0.0000000000000000</nm:col>
<nm:col nm:cname='ETA5'>0.0000000000000000</nm:col>
</nm:row>
</nm:etashrinksd>
<nm:etashrinkvr>
<nm:row nm:rname='SUBPOP1'>
<nm:col nm:cname='ETA1'>33.015279063339662</nm:col>
<nm:col nm:cname='ETA2'>12.235625764552172</nm:col>
<nm:col nm:cname='ETA3'>1.7886716513038081</nm:col>
<nm:col nm:cname='ETA4'>0.0000000000000000</nm:col>
<nm:col nm:cname='ETA5'>0.0000000000000000</nm:col>
</nm:row>
</nm:etashrinkvr>
<nm:ebvshrinksd>
<nm:row nm:rname='SUBPOP1'>
<nm:col nm:cname='EBV1'>18.021806973452126</nm:col>
<nm:col nm:cname='EBV2'>6.3320120841729555</nm:col>
<nm:col nm:cname='EBV3'>0.87799528662068083</nm:col>
<nm:col nm:cname='EBV4'>0.0000000000000000</nm:col>
<nm:col nm:cname='EBV5'>0.0000000000000000</nm:col>
</nm:row>
</nm:ebvshrinksd>
<nm:ebvshrinkvr>
<nm:row nm:rname='SUBPOP1'>
<nm:col nm:cname='EBV1'>32.795758681020573</nm:col>
<nm:col nm:cname='EBV2'>12.263080398004776</nm:col>
<nm:col nm:cname='EBV3'>1.7482818160080837</nm:col>
<nm:col nm:cname='EBV4'>0.0000000000000000</nm:col>
<nm:col nm:cname='EBV5'>0.0000000000000000</nm:col>
</nm:row>
</nm:ebvshrinkvr>
<nm:relativeinf>
<nm:row nm:rname='SUBPOP1'>
<nm:col nm:cname='REL1'>37.623180703136249</nm:col>
<nm:col nm:cname='REL2'>80.680298338576534</nm:col>
<nm:col nm:cname='REL3'>96.891057801356951</nm:col>
<nm:col nm:cname='REL4'>0.0000000000000000</nm:col>
<nm:col nm:cname='REL5'>0.0000000000000000</nm:col>
</nm:row>
</nm:relativeinf>
<nm:epsshrinksd>
<nm:row nm:rname='SUBPOP1'>
<nm:col nm:cname='EPS1'>5.2753674427238550</nm:col>
</nm:row>
</nm:epsshrinksd>
<nm:epsshrinkvr>
<nm:row nm:rname='SUBPOP1'>
<nm:col nm:cname='EPS1'>10.272439868890205</nm:col>
</nm:row>
</nm:epsshrinkvr>
<nm:estimation_elapsed_time>18.25</nm:estimation_elapsed_time>
<nm:covariance_information><![CDATA[
]]></nm:covariance_information>
<nm:covariance_status nm:error='0' nm:numnegeigenvalues='-1' nm:mineigenvalue='0.0000000000000000' nm:maxeigenvalue='0.0000000000000000' nm:rms='0.0000000000000000'/>
<nm:covariance_elapsed_time>13.03</nm:covariance_elapsed_time>
<nm:final_objective_function_text>MINIMUM VALUE OF OBJECTIVE FUNCTION</nm:final_objective_function_text>
<nm:final_objective_function>30997.907860469291</nm:final_objective_function>
<nm:theta>
<nm:val nm:name='1'>0.43359154559132412</nm:val>
<nm:val nm:name='2'>4.1187632441358479</nm:val>
<nm:val nm:name='3'>1.1150333634459864</nm:val>
<nm:val nm:name='4'>4.2099104949484625</nm:val>
<nm:val nm:name='5'>1.2863070597629533</nm:val>
</nm:theta>
<nm:omega>
<nm:row nm:rname='1'>
<nm:col nm:cname='1'>0.22060566422057484</nm:col>
</nm:row>
<nm:row nm:rname='2'>
<nm:col nm:cname='1'>6.9008829308263867E-002</nm:col>
<nm:col nm:cname='2'>8.2692204529783334E-002</nm:col>
</nm:row>
<nm:row nm:rname='3'>
<nm:col nm:cname='1'>0.13400861579881215</nm:col>
<nm:col nm:cname='2'>7.3502705529682549E-002</nm:col>
<nm:col nm:cname='3'>0.16911604770560063</nm:col>
</nm:row>
<nm:row nm:rname='4'>
<nm:col nm:cname='1'>0.0000000000000000</nm:col>
<nm:col nm:cname='2'>0.0000000000000000</nm:col>
<nm:col nm:cname='3'>0.0000000000000000</nm:col>
<nm:col nm:cname='4'>0.0000000000000000</nm:col>
</nm:row>
<nm:row nm:rname='5'>
<nm:col nm:cname='1'>0.0000000000000000</nm:col>
<nm:col nm:cname='2'>0.0000000000000000</nm:col>
<nm:col nm:cname='3'>0.0000000000000000</nm:col>
<nm:col nm:cname='4'>0.0000000000000000</nm:col>
<nm:col nm:cname='5'>0.0000000000000000</nm:col>
</nm:row>
</nm:omega>
<nm:sigma>
<nm:row nm:rname='1'>
<nm:col nm:cname='1'>3.9916731051881489E-002</nm:col>
</nm:row>
</nm:sigma>
<nm:omegac>
<nm:row nm:rname='1'>
<nm:col nm:cname='1'>0.46968677245646895</nm:col>
</nm:row>
<nm:row nm:rname='2'>
<nm:col nm:cname='1'>0.51093310780611323</nm:col>
<nm:col nm:cname='2'>0.28756252281857475</nm:col>
</nm:row>
<nm:row nm:rname='3'>
<nm:col nm:cname='1'>0.69379630332804210</nm:col>
<nm:col nm:cname='2'>0.62155366242851795</nm:col>
<nm:col nm:cname='3'>0.41123721585673717</nm:col>
</nm:row>
<nm:row nm:rname='4'>
<nm:col nm:cname='1'>0.0000000000000000</nm:col>
<nm:col nm:cname='2'>0.0000000000000000</nm:col>
<nm:col nm:cname='3'>0.0000000000000000</nm:col>
<nm:col nm:cname='4'>0.0000000000000000</nm:col>
</nm:row>
<nm:row nm:rname='5'>
<nm:col nm:cname='1'>0.0000000000000000</nm:col>
<nm:col nm:cname='2'>0.0000000000000000</nm:col>
<nm:col nm:cname='3'>0.0000000000000000</nm:col>
<nm:col nm:cname='4'>0.0000000000000000</nm:col>
<nm:col nm:cname='5'>0.0000000000000000</nm:col>
</nm:row>
</nm:omegac>
<nm:sigmac>
<nm:row nm:rname='1'>
<nm:col nm:cname='1'>0.19979171917745112</nm:col>
</nm:row>
</nm:sigmac>
<nm:thetase>
<nm:val nm:name='1'>6.2874439051833167E-002</nm:val>
<nm:val nm:name='2'>2.7627259294469686E-002</nm:val>
<nm:val nm:name='3'>3.2847537370988632E-002</nm:val>
<nm:val nm:name='4'>1.9248549340957165E-002</nm:val>
<nm:val nm:name='5'>3.5426154706992584E-002</nm:val>
</nm:thetase>
<nm:omegase>
<nm:row nm:rname='1'>
<nm:col nm:cname='1'>5.2979876710937006E-002</nm:col>
</nm:row>
<nm:row nm:rname='2'>
<nm:col nm:cname='1'>1.9961737176590593E-002</nm:col>
<nm:col nm:cname='2'>9.8254662444527633E-003</nm:col>
</nm:row>
<nm:row nm:rname='3'>
<nm:col nm:cname='1'>2.3587401092594936E-002</nm:col>
<nm:col nm:cname='2'>1.0548148602069568E-002</nm:col>
<nm:col nm:cname='3'>1.9728927759020406E-002</nm:col>
</nm:row>
<nm:row nm:rname='4'>
<nm:col nm:cname='1'>10000000000.000000</nm:col>
<nm:col nm:cname='2'>10000000000.000000</nm:col>
<nm:col nm:cname='3'>10000000000.000000</nm:col>
<nm:col nm:cname='4'>10000000000.000000</nm:col>
</nm:row>
<nm:row nm:rname='5'>
<nm:col nm:cname='1'>10000000000.000000</nm:col>
<nm:col nm:cname='2'>10000000000.000000</nm:col>
<nm:col nm:cname='3'>10000000000.000000</nm:col>
<nm:col nm:cname='4'>10000000000.000000</nm:col>
<nm:col nm:cname='5'>10000000000.000000</nm:col>
</nm:row>
</nm:omegase>
<nm:sigmase>
<nm:row nm:rname='1'>
<nm:col nm:cname='1'>1.2259517179966292E-003</nm:col>
</nm:row>
</nm:sigmase>
<nm:omegacse>
<nm:row nm:rname='1'>
<nm:col nm:cname='1'>5.6399157712970542E-002</nm:col>
</nm:row>
<nm:row nm:rname='2'>
<nm:col nm:cname='1'>9.7469815478428562E-002</nm:col>
<nm:col nm:cname='2'>1.7084052101343745E-002</nm:col>
</nm:row>
<nm:row nm:rname='3'>
<nm:col nm:cname='1'>6.8605504831158015E-002</nm:col>
<nm:col nm:cname='2'>5.2388846289566950E-002</nm:col>
<nm:col nm:cname='3'>2.3987283979051862E-002</nm:col>
</nm:row>
<nm:row nm:rname='4'>
<nm:col nm:cname='1'>10000000000.000000</nm:col>
<nm:col nm:cname='2'>10000000000.000000</nm:col>
<nm:col nm:cname='3'>10000000000.000000</nm:col>
<nm:col nm:cname='4'>10000000000.000000</nm:col>
</nm:row>
<nm:row nm:rname='5'>
<nm:col nm:cname='1'>10000000000.000000</nm:col>
<nm:col nm:cname='2'>10000000000.000000</nm:col>
<nm:col nm:cname='3'>10000000000.000000</nm:col>
<nm:col nm:cname='4'>10000000000.000000</nm:col>
<nm:col nm:cname='5'>10000000000.000000</nm:col>
</nm:row>
</nm:omegacse>
<nm:sigmacse>
<nm:row nm:rname='1'>
<nm:col nm:cname='1'>3.0680744002902411E-003</nm:col>
</nm:row>
</nm:sigmacse>
<nm:covariance>
<nm:row nm:rname='THETA1'>
<nm:col nm:cname='THETA1'>3.9531950860826831E-003</nm:col>
</nm:row>
<nm:row nm:rname='THETA2'>
<nm:col nm:cname='THETA1'>1.0443384141416703E-003</nm:col>
<nm:col nm:cname='THETA2'>7.6326545612386161E-004</nm:col>
</nm:row>
<nm:row nm:rname='THETA3'>
<nm:col nm:cname='THETA1'>9.4955333082094638E-004</nm:col>
<nm:col nm:cname='THETA2'>4.9294959003299264E-004</nm:col>
<nm:col nm:cname='THETA3'>1.0789607113384950E-003</nm:col>
</nm:row>
<nm:row nm:rname='THETA4'>
<nm:col nm:cname='THETA1'>-3.0076769495257239E-004</nm:col>
<nm:col nm:cname='THETA2'>-9.5934096239411805E-005</nm:col>
<nm:col nm:cname='THETA3'>-2.4599033728855572E-006</nm:col>
<nm:col nm:cname='THETA4'>3.7050665173126254E-004</nm:col>
</nm:row>
<nm:row nm:rname='THETA5'>
<nm:col nm:cname='THETA1'>-1.0637643159166700E-003</nm:col>
<nm:col nm:cname='THETA2'>-4.4085912822553131E-004</nm:col>
<nm:col nm:cname='THETA3'>-1.5068492386939312E-004</nm:col>
<nm:col nm:cname='THETA4'>1.2166095935505376E-004</nm:col>
<nm:col nm:cname='THETA5'>1.2550124373237729E-003</nm:col>
</nm:row>
<nm:row nm:rname='OMEGA(1,1)'>
<nm:col nm:cname='THETA1'>9.4618893053391266E-004</nm:col>
<nm:col nm:cname='THETA2'>9.7779290002313654E-005</nm:col>
<nm:col nm:cname='THETA3'>3.2807919022146347E-005</nm:col>
<nm:col nm:cname='THETA4'>-8.0239100464864904E-005</nm:col>
<nm:col nm:cname='THETA5'>-6.1199362671652443E-005</nm:col>
<nm:col nm:cname='OMEGA(1,1)'>2.8068673363060852E-003</nm:col>
</nm:row>
<nm:row nm:rname='OMEGA(1,2)'>
<nm:col nm:cname='THETA1'>1.8213639367422555E-004</nm:col>
<nm:col nm:cname='THETA2'>-9.0957615306251520E-006</nm:col>
<nm:col nm:cname='THETA3'>6.5578900780510337E-005</nm:col>
<nm:col nm:cname='THETA4'>-2.2120624636096697E-005</nm:col>
<nm:col nm:cname='THETA5'>1.3757891863876490E-004</nm:col>
<nm:col nm:cname='OMEGA(1,1)'>6.8618206417730347E-004</nm:col>
<nm:col nm:cname='OMEGA(1,2)'>3.9847095110727903E-004</nm:col>
</nm:row>
<nm:row nm:rname='OMEGA(1,3)'>
<nm:col nm:cname='THETA1'>3.9352347566846231E-004</nm:col>
<nm:col nm:cname='THETA2'>7.7639394630238135E-005</nm:col>
<nm:col nm:cname='THETA3'>2.4888165898875468E-005</nm:col>
<nm:col nm:cname='THETA4'>-4.9953893796824633E-005</nm:col>
<nm:col nm:cname='THETA5'>-8.9682967490001306E-007</nm:col>
<nm:col nm:cname='OMEGA(1,1)'>9.3221986189919869E-004</nm:col>
<nm:col nm:cname='OMEGA(1,2)'>3.0570517581053765E-004</nm:col>
<nm:col nm:cname='OMEGA(1,3)'>5.5636549030294881E-004</nm:col>
</nm:row>
<nm:row nm:rname='OMEGA(1,4)'>
<nm:col nm:cname='THETA1'>0.0000000000000000</nm:col>
<nm:col nm:cname='THETA2'>0.0000000000000000</nm:col>
<nm:col nm:cname='THETA3'>0.0000000000000000</nm:col>
<nm:col nm:cname='THETA4'>0.0000000000000000</nm:col>
<nm:col nm:cname='THETA5'>0.0000000000000000</nm:col>
<nm:col nm:cname='OMEGA(1,1)'>0.0000000000000000</nm:col>
<nm:col nm:cname='OMEGA(1,2)'>0.0000000000000000</nm:col>
<nm:col nm:cname='OMEGA(1,3)'>0.0000000000000000</nm:col>
<nm:col nm:cname='OMEGA(1,4)'>0.0000000000000000</nm:col>
</nm:row>
<nm:row nm:rname='OMEGA(1,5)'>
<nm:col nm:cname='THETA1'>0.0000000000000000</nm:col>
<nm:col nm:cname='THETA2'>0.0000000000000000</nm:col>
<nm:col nm:cname='THETA3'>0.0000000000000000</nm:col>
<nm:col nm:cname='THETA4'>0.0000000000000000</nm:col>
<nm:col nm:cname='THETA5'>0.0000000000000000</nm:col>
<nm:col nm:cname='OMEGA(1,1)'>0.0000000000000000</nm:col>
<nm:col nm:cname='OMEGA(1,2)'>0.0000000000000000</nm:col>
<nm:col nm:cname='OMEGA(1,3)'>0.0000000000000000</nm:col>
<nm:col nm:cname='OMEGA(1,4)'>0.0000000000000000</nm:col>
<nm:col nm:cname='OMEGA(1,5)'>0.0000000000000000</nm:col>
</nm:row>
<nm:row nm:rname='OMEGA(2,2)'>
<nm:col nm:cname='THETA1'>1.5383283956871991E-005</nm:col>
<nm:col nm:cname='THETA2'>-1.1697450064565675E-005</nm:col>
<nm:col nm:cname='THETA3'>1.9540015181625619E-005</nm:col>
<nm:col nm:cname='THETA4'>-1.1265988804599487E-005</nm:col>
<nm:col nm:cname='THETA5'>8.2686101855047401E-005</nm:col>
<nm:col nm:cname='OMEGA(1,1)'>1.8312189654710827E-004</nm:col>
<nm:col nm:cname='OMEGA(1,2)'>1.4366179097490805E-004</nm:col>
<nm:col nm:cname='OMEGA(1,3)'>1.0146557400025425E-004</nm:col>
<nm:col nm:cname='OMEGA(1,4)'>0.0000000000000000</nm:col>
<nm:col nm:cname='OMEGA(1,5)'>0.0000000000000000</nm:col>
<nm:col nm:cname='OMEGA(2,2)'>9.6539786920880676E-005</nm:col>
</nm:row>
<nm:row nm:rname='OMEGA(2,3)'>
<nm:col nm:cname='THETA1'>4.0852724639955809E-005</nm:col>
<nm:col nm:cname='THETA2'>-9.0919938051981852E-008</nm:col>
<nm:col nm:cname='THETA3'>3.2304899079515062E-005</nm:col>
<nm:col nm:cname='THETA4'>1.0968022907926477E-007</nm:col>
<nm:col nm:cname='THETA5'>6.7158044848613562E-005</nm:col>
<nm:col nm:cname='OMEGA(1,1)'>1.8681646579377895E-004</nm:col>
<nm:col nm:cname='OMEGA(1,2)'>1.4300365816681895E-004</nm:col>
<nm:col nm:cname='OMEGA(1,3)'>1.5154688170437489E-004</nm:col>
<nm:col nm:cname='OMEGA(1,4)'>0.0000000000000000</nm:col>
<nm:col nm:cname='OMEGA(1,5)'>0.0000000000000000</nm:col>
<nm:col nm:cname='OMEGA(2,2)'>7.3787742221170704E-005</nm:col>
<nm:col nm:cname='OMEGA(2,3)'>1.1126343893134218E-004</nm:col>
</nm:row>
<nm:row nm:rname='OMEGA(2,4)'>
<nm:col nm:cname='THETA1'>0.0000000000000000</nm:col>
<nm:col nm:cname='THETA2'>0.0000000000000000</nm:col>
<nm:col nm:cname='THETA3'>0.0000000000000000</nm:col>
<nm:col nm:cname='THETA4'>0.0000000000000000</nm:col>
<nm:col nm:cname='THETA5'>0.0000000000000000</nm:col>
<nm:col nm:cname='OMEGA(1,1)'>0.0000000000000000</nm:col>
<nm:col nm:cname='OMEGA(1,2)'>0.0000000000000000</nm:col>
<nm:col nm:cname='OMEGA(1,3)'>0.0000000000000000</nm:col>
<nm:col nm:cname='OMEGA(1,4)'>0.0000000000000000</nm:col>
<nm:col nm:cname='OMEGA(1,5)'>0.0000000000000000</nm:col>
<nm:col nm:cname='OMEGA(2,2)'>0.0000000000000000</nm:col>
<nm:col nm:cname='OMEGA(2,3)'>0.0000000000000000</nm:col>
<nm:col nm:cname='OMEGA(2,4)'>0.0000000000000000</nm:col>
</nm:row>
<nm:row nm:rname='OMEGA(2,5)'>
<nm:col nm:cname='THETA1'>0.0000000000000000</nm:col>
<nm:col nm:cname='THETA2'>0.0000000000000000</nm:col>
<nm:col nm:cname='THETA3'>0.0000000000000000</nm:col>
<nm:col nm:cname='THETA4'>0.0000000000000000</nm:col>
<nm:col nm:cname='THETA5'>0.0000000000000000</nm:col>
<nm:col nm:cname='OMEGA(1,1)'>0.0000000000000000</nm:col>
<nm:col nm:cname='OMEGA(1,2)'>0.0000000000000000</nm:col>
<nm:col nm:cname='OMEGA(1,3)'>0.0000000000000000</nm:col>
<nm:col nm:cname='OMEGA(1,4)'>0.0000000000000000</nm:col>
<nm:col nm:cname='OMEGA(1,5)'>0.0000000000000000</nm:col>
<nm:col nm:cname='OMEGA(2,2)'>0.0000000000000000</nm:col>
<nm:col nm:cname='OMEGA(2,3)'>0.0000000000000000</nm:col>
<nm:col nm:cname='OMEGA(2,4)'>0.0000000000000000</nm:col>
<nm:col nm:cname='OMEGA(2,5)'>0.0000000000000000</nm:col>
</nm:row>
<nm:row nm:rname='OMEGA(3,3)'>
<nm:col nm:cname='THETA1'>-8.8000850203676217E-006</nm:col>
<nm:col nm:cname='THETA2'>5.0822339944193335E-005</nm:col>
<nm:col nm:cname='THETA3'>-1.2442184739287724E-004</nm:col>
<nm:col nm:cname='THETA4'>7.9640525845166127E-006</nm:col>
<nm:col nm:cname='THETA5'>-3.1216931124990947E-005</nm:col>
<nm:col nm:cname='OMEGA(1,1)'>1.1288782633929908E-004</nm:col>
<nm:col nm:cname='OMEGA(1,2)'>7.6029274025335951E-005</nm:col>
<nm:col nm:cname='OMEGA(1,3)'>2.0404940000027456E-004</nm:col>
<nm:col nm:cname='OMEGA(1,4)'>0.0000000000000000</nm:col>
<nm:col nm:cname='OMEGA(1,5)'>0.0000000000000000</nm:col>
<nm:col nm:cname='OMEGA(2,2)'>2.8629875105368015E-005</nm:col>
<nm:col nm:cname='OMEGA(2,3)'>1.1567209606795779E-004</nm:col>
<nm:col nm:cname='OMEGA(2,4)'>0.0000000000000000</nm:col>
<nm:col nm:cname='OMEGA(2,5)'>0.0000000000000000</nm:col>
<nm:col nm:cname='OMEGA(3,3)'>3.8923059052064596E-004</nm:col>
</nm:row>
<nm:row nm:rname='OMEGA(3,4)'>
<nm:col nm:cname='THETA1'>0.0000000000000000</nm:col>
<nm:col nm:cname='THETA2'>0.0000000000000000</nm:col>
<nm:col nm:cname='THETA3'>0.0000000000000000</nm:col>
<nm:col nm:cname='THETA4'>0.0000000000000000</nm:col>
<nm:col nm:cname='THETA5'>0.0000000000000000</nm:col>
<nm:col nm:cname='OMEGA(1,1)'>0.0000000000000000</nm:col>
<nm:col nm:cname='OMEGA(1,2)'>0.0000000000000000</nm:col>
<nm:col nm:cname='OMEGA(1,3)'>0.0000000000000000</nm:col>
<nm:col nm:cname='OMEGA(1,4)'>0.0000000000000000</nm:col>
<nm:col nm:cname='OMEGA(1,5)'>0.0000000000000000</nm:col>
<nm:col nm:cname='OMEGA(2,2)'>0.0000000000000000</nm:col>
<nm:col nm:cname='OMEGA(2,3)'>0.0000000000000000</nm:col>
<nm:col nm:cname='OMEGA(2,4)'>0.0000000000000000</nm:col>
<nm:col nm:cname='OMEGA(2,5)'>0.0000000000000000</nm:col>
<nm:col nm:cname='OMEGA(3,3)'>0.0000000000000000</nm:col>
<nm:col nm:cname='OMEGA(3,4)'>0.0000000000000000</nm:col>
</nm:row>
<nm:row nm:rname='OMEGA(3,5)'>
<nm:col nm:cname='THETA1'>0.0000000000000000</nm:col>
<nm:col nm:cname='THETA2'>0.0000000000000000</nm:col>
<nm:col nm:cname='THETA3'>0.0000000000000000</nm:col>
<nm:col nm:cname='THETA4'>0.0000000000000000</nm:col>
<nm:col nm:cname='THETA5'>0.0000000000000000</nm:col>
<nm:col nm:cname='OMEGA(1,1)'>0.0000000000000000</nm:col>
<nm:col nm:cname='OMEGA(1,2)'>0.0000000000000000</nm:col>
<nm:col nm:cname='OMEGA(1,3)'>0.0000000000000000</nm:col>
<nm:col nm:cname='OMEGA(1,4)'>0.0000000000000000</nm:col>
<nm:col nm:cname='OMEGA(1,5)'>0.0000000000000000</nm:col>
<nm:col nm:cname='OMEGA(2,2)'>0.0000000000000000</nm:col>
<nm:col nm:cname='OMEGA(2,3)'>0.0000000000000000</nm:col>
<nm:col nm:cname='OMEGA(2,4)'>0.0000000000000000</nm:col>
<nm:col nm:cname='OMEGA(2,5)'>0.0000000000000000</nm:col>
<nm:col nm:cname='OMEGA(3,3)'>0.0000000000000000</nm:col>
<nm:col nm:cname='OMEGA(3,4)'>0.0000000000000000</nm:col>
<nm:col nm:cname='OMEGA(3,5)'>0.0000000000000000</nm:col>
</nm:row>
<nm:row nm:rname='OMEGA(4,4)'>
<nm:col nm:cname='THETA1'>0.0000000000000000</nm:col>
<nm:col nm:cname='THETA2'>0.0000000000000000</nm:col>
<nm:col nm:cname='THETA3'>0.0000000000000000</nm:col>
<nm:col nm:cname='THETA4'>0.0000000000000000</nm:col>
<nm:col nm:cname='THETA5'>0.0000000000000000</nm:col>
<nm:col nm:cname='OMEGA(1,1)'>0.0000000000000000</nm:col>
<nm:col nm:cname='OMEGA(1,2)'>0.0000000000000000</nm:col>
<nm:col nm:cname='OMEGA(1,3)'>0.0000000000000000</nm:col>
<nm:col nm:cname='OMEGA(1,4)'>0.0000000000000000</nm:col>
<nm:col nm:cname='OMEGA(1,5)'>0.0000000000000000</nm:col>
<nm:col nm:cname='OMEGA(2,2)'>0.0000000000000000</nm:col>
<nm:col nm:cname='OMEGA(2,3)'>0.0000000000000000</nm:col>
<nm:col nm:cname='OMEGA(2,4)'>0.0000000000000000</nm:col>
<nm:col nm:cname='OMEGA(2,5)'>0.0000000000000000</nm:col>
<nm:col nm:cname='OMEGA(3,3)'>0.0000000000000000</nm:col>
<nm:col nm:cname='OMEGA(3,4)'>0.0000000000000000</nm:col>
<nm:col nm:cname='OMEGA(3,5)'>0.0000000000000000</nm:col>
<nm:col nm:cname='OMEGA(4,4)'>0.0000000000000000</nm:col>
</nm:row>
<nm:row nm:rname='OMEGA(4,5)'>
<nm:col nm:cname='THETA1'>0.0000000000000000</nm:col>
<nm:col nm:cname='THETA2'>0.0000000000000000</nm:col>
<nm:col nm:cname='THETA3'>0.0000000000000000</nm:col>
<nm:col nm:cname='THETA4'>0.0000000000000000</nm:col>
<nm:col nm:cname='THETA5'>0.0000000000000000</nm:col>
<nm:col nm:cname='OMEGA(1,1)'>0.0000000000000000</nm:col>
<nm:col nm:cname='OMEGA(1,2)'>0.0000000000000000</nm:col>
<nm:col nm:cname='OMEGA(1,3)'>0.0000000000000000</nm:col>
<nm:col nm:cname='OMEGA(1,4)'>0.0000000000000000</nm:col>
<nm:col nm:cname='OMEGA(1,5)'>0.0000000000000000</nm:col>
<nm:col nm:cname='OMEGA(2,2)'>0.0000000000000000</nm:col>
<nm:col nm:cname='OMEGA(2,3)'>0.0000000000000000</nm:col>
<nm:col nm:cname='OMEGA(2,4)'>0.0000000000000000</nm:col>
<nm:col nm:cname='OMEGA(2,5)'>0.0000000000000000</nm:col>
<nm:col nm:cname='OMEGA(3,3)'>0.0000000000000000</nm:col>
<nm:col nm:cname='OMEGA(3,4)'>0.0000000000000000</nm:col>
<nm:col nm:cname='OMEGA(3,5)'>0.0000000000000000</nm:col>
<nm:col nm:cname='OMEGA(4,4)'>0.0000000000000000</nm:col>
<nm:col nm:cname='OMEGA(4,5)'>0.0000000000000000</nm:col>
</nm:row>
<nm:row nm:rname='OMEGA(5,5)'>
<nm:col nm:cname='THETA1'>0.0000000000000000</nm:col>
<nm:col nm:cname='THETA2'>0.0000000000000000</nm:col>
<nm:col nm:cname='THETA3'>0.0000000000000000</nm:col>
<nm:col nm:cname='THETA4'>0.0000000000000000</nm:col>
<nm:col nm:cname='THETA5'>0.0000000000000000</nm:col>
<nm:col nm:cname='OMEGA(1,1)'>0.0000000000000000</nm:col>
<nm:col nm:cname='OMEGA(1,2)'>0.0000000000000000</nm:col>
<nm:col nm:cname='OMEGA(1,3)'>0.0000000000000000</nm:col>
<nm:col nm:cname='OMEGA(1,4)'>0.0000000000000000</nm:col>
<nm:col nm:cname='OMEGA(1,5)'>0.0000000000000000</nm:col>
<nm:col nm:cname='OMEGA(2,2)'>0.0000000000000000</nm:col>
<nm:col nm:cname='OMEGA(2,3)'>0.0000000000000000</nm:col>
<nm:col nm:cname='OMEGA(2,4)'>0.0000000000000000</nm:col>
<nm:col nm:cname='OMEGA(2,5)'>0.0000000000000000</nm:col>
<nm:col nm:cname='OMEGA(3,3)'>0.0000000000000000</nm:col>
<nm:col nm:cname='OMEGA(3,4)'>0.0000000000000000</nm:col>
<nm:col nm:cname='OMEGA(3,5)'>0.0000000000000000</nm:col>
<nm:col nm:cname='OMEGA(4,4)'>0.0000000000000000</nm:col>
<nm:col nm:cname='OMEGA(4,5)'>0.0000000000000000</nm:col>
<nm:col nm:cname='OMEGA(5,5)'>0.0000000000000000</nm:col>
</nm:row>
<nm:row nm:rname='SIGMA(1,1)'>
<nm:col nm:cname='THETA1'>6.0888675979188524E-006</nm:col>
<nm:col nm:cname='THETA2'>2.1656833692562118E-006</nm:col>
<nm:col nm:cname='THETA3'>6.5159360669715137E-006</nm:col>
<nm:col nm:cname='THETA4'>1.7517131580144091E-006</nm:col>
<nm:col nm:cname='THETA5'>2.2130205359156975E-007</nm:col>
<nm:col nm:cname='OMEGA(1,1)'>-9.3003020687237016E-006</nm:col>
<nm:col nm:cname='OMEGA(1,2)'>-1.1997234100420587E-006</nm:col>
<nm:col nm:cname='OMEGA(1,3)'>7.4864876720192990E-007</nm:col>
<nm:col nm:cname='OMEGA(1,4)'>0.0000000000000000</nm:col>
<nm:col nm:cname='OMEGA(1,5)'>0.0000000000000000</nm:col>
<nm:col nm:cname='OMEGA(2,2)'>-1.2328125220470857E-006</nm:col>
<nm:col nm:cname='OMEGA(2,3)'>5.1795893331149537E-007</nm:col>
<nm:col nm:cname='OMEGA(2,4)'>0.0000000000000000</nm:col>
<nm:col nm:cname='OMEGA(2,5)'>0.0000000000000000</nm:col>
<nm:col nm:cname='OMEGA(3,3)'>3.0294646793133499E-006</nm:col>
<nm:col nm:cname='OMEGA(3,4)'>0.0000000000000000</nm:col>
<nm:col nm:cname='OMEGA(3,5)'>0.0000000000000000</nm:col>
<nm:col nm:cname='OMEGA(4,4)'>0.0000000000000000</nm:col>
<nm:col nm:cname='OMEGA(4,5)'>0.0000000000000000</nm:col>
<nm:col nm:cname='OMEGA(5,5)'>0.0000000000000000</nm:col>
<nm:col nm:cname='SIGMA(1,1)'>1.5029576148588866E-006</nm:col>
</nm:row>
</nm:covariance>
<nm:correlation>
<nm:row nm:rname='THETA1'>
<nm:col nm:cname='THETA1'>6.2874439051833167E-002</nm:col>
</nm:row>
<nm:row nm:rname='THETA2'>
<nm:col nm:cname='THETA1'>0.60121433328905516</nm:col>
<nm:col nm:cname='THETA2'>2.7627259294469686E-002</nm:col>
</nm:row>
<nm:row nm:rname='THETA3'>
<nm:col nm:cname='THETA1'>0.45977189770431293</nm:col>
<nm:col nm:cname='THETA2'>0.54320266328569933</nm:col>
<nm:col nm:cname='THETA3'>3.2847537370988632E-002</nm:col>
</nm:row>
<nm:row nm:rname='THETA4'>
<nm:col nm:cname='THETA1'>-0.24851869211066513</nm:col>
<nm:col nm:cname='THETA2'>-0.18040026873778892</nm:col>
<nm:col nm:cname='THETA3'>-3.8906057823334932E-003</nm:col>
<nm:col nm:cname='THETA4'>1.9248549340957165E-002</nm:col>
</nm:row>
<nm:row nm:rname='THETA5'>
<nm:col nm:cname='THETA1'>-0.47758126271782747</nm:col>
<nm:col nm:cname='THETA2'>-0.45044110883263372</nm:col>
<nm:col nm:cname='THETA3'>-0.12949201018419076</nm:col>
<nm:col nm:cname='THETA4'>0.17841411795527992</nm:col>
<nm:col nm:cname='THETA5'>3.5426154706992584E-002</nm:col>
</nm:row>
<nm:row nm:rname='OMEGA(1,1)'>
<nm:col nm:cname='THETA1'>0.28404869358575086</nm:col>
<nm:col nm:cname='THETA2'>6.6803333184416613E-002</nm:col>
<nm:col nm:cname='THETA3'>1.8852325327492314E-002</nm:col>
<nm:col nm:cname='THETA4'>-7.8682310295671812E-002</nm:col>
<nm:col nm:cname='THETA5'>-3.2607082421253333E-002</nm:col>
<nm:col nm:cname='OMEGA(1,1)'>5.2979876710937006E-002</nm:col>
</nm:row>
<nm:row nm:rname='OMEGA(1,2)'>
<nm:col nm:cname='THETA1'>0.14511899984830351</nm:col>
<nm:col nm:cname='THETA2'>-1.6493124172479345E-002</nm:col>
<nm:col nm:cname='THETA3'>0.10001450370455563</nm:col>
<nm:col nm:cname='THETA4'>-5.7570638805851664E-002</nm:col>
<nm:col nm:cname='THETA5'>0.19454924220729355</nm:col>
<nm:col nm:cname='OMEGA(1,1)'>0.64882875001868823</nm:col>
<nm:col nm:cname='OMEGA(1,2)'>1.9961737176590593E-002</nm:col>
</nm:row>
<nm:row nm:rname='OMEGA(1,3)'>
<nm:col nm:cname='THETA1'>0.26534837346190293</nm:col>
<nm:col nm:cname='THETA2'>0.11914182399164319</nm:col>
<nm:col nm:cname='THETA3'>3.2122547910085432E-002</nm:col>
<nm:col nm:cname='THETA4'>-0.11002496762797323</nm:col>
<nm:col nm:cname='THETA5'>-1.0732622721590548E-003</nm:col>
<nm:col nm:cname='OMEGA(1,1)'>0.74598022733881475</nm:col>
<nm:col nm:cname='OMEGA(1,2)'>0.64926854981835191</nm:col>
<nm:col nm:cname='OMEGA(1,3)'>2.3587401092594936E-002</nm:col>
</nm:row>
<nm:row nm:rname='OMEGA(1,4)'>
<nm:col nm:cname='THETA1'>0.0000000000000000</nm:col>
<nm:col nm:cname='THETA2'>0.0000000000000000</nm:col>
<nm:col nm:cname='THETA3'>0.0000000000000000</nm:col>
<nm:col nm:cname='THETA4'>0.0000000000000000</nm:col>
<nm:col nm:cname='THETA5'>0.0000000000000000</nm:col>
<nm:col nm:cname='OMEGA(1,1)'>0.0000000000000000</nm:col>
<nm:col nm:cname='OMEGA(1,2)'>0.0000000000000000</nm:col>
<nm:col nm:cname='OMEGA(1,3)'>0.0000000000000000</nm:col>
<nm:col nm:cname='OMEGA(1,4)'>0.0000000000000000</nm:col>
</nm:row>
<nm:row nm:rname='OMEGA(1,5)'>
<nm:col nm:cname='THETA1'>0.0000000000000000</nm:col>
<nm:col nm:cname='THETA2'>0.0000000000000000</nm:col>
<nm:col nm:cname='THETA3'>0.0000000000000000</nm:col>
<nm:col nm:cname='THETA4'>0.0000000000000000</nm:col>
<nm:col nm:cname='THETA5'>0.0000000000000000</nm:col>
<nm:col nm:cname='OMEGA(1,1)'>0.0000000000000000</nm:col>
<nm:col nm:cname='OMEGA(1,2)'>0.0000000000000000</nm:col>
<nm:col nm:cname='OMEGA(1,3)'>0.0000000000000000</nm:col>
<nm:col nm:cname='OMEGA(1,4)'>0.0000000000000000</nm:col>
<nm:col nm:cname='OMEGA(1,5)'>0.0000000000000000</nm:col>
</nm:row>
<nm:row nm:rname='OMEGA(2,2)'>
<nm:col nm:cname='THETA1'>2.4901285365567849E-002</nm:col>
<nm:col nm:cname='THETA2'>-4.3092354922551430E-002</nm:col>
<nm:col nm:cname='THETA3'>6.0543693729124659E-002</nm:col>
<nm:col nm:cname='THETA4'>-5.9568702791701067E-002</nm:col>
<nm:col nm:cname='THETA5'>0.23755016435994178</nm:col>
<nm:col nm:cname='OMEGA(1,1)'>0.35178406763202219</nm:col>
<nm:col nm:cname='OMEGA(1,2)'>0.73246988746633401</nm:col>
<nm:col nm:cname='OMEGA(1,3)'>0.43780977768190088</nm:col>
<nm:col nm:cname='OMEGA(1,4)'>0.0000000000000000</nm:col>
<nm:col nm:cname='OMEGA(1,5)'>0.0000000000000000</nm:col>
<nm:col nm:cname='OMEGA(2,2)'>9.8254662444527633E-003</nm:col>
</nm:row>
<nm:row nm:rname='OMEGA(2,3)'>
<nm:col nm:cname='THETA1'>6.1598574769335092E-002</nm:col>
<nm:col nm:cname='THETA2'>-3.1199317081113931E-004</nm:col>
<nm:col nm:cname='THETA3'>9.3237223822048826E-002</nm:col>
<nm:col nm:cname='THETA4'>5.4019940898944474E-004</nm:col>
<nm:col nm:cname='THETA5'>0.17972057102317290</nm:col>
<nm:col nm:cname='OMEGA(1,1)'>0.33429352827963416</nm:col>
<nm:col nm:cname='OMEGA(1,2)'>0.67916074265840887</nm:col>
<nm:col nm:cname='OMEGA(1,3)'>0.60910290807769030</nm:col>
<nm:col nm:cname='OMEGA(1,4)'>0.0000000000000000</nm:col>
<nm:col nm:cname='OMEGA(1,5)'>0.0000000000000000</nm:col>
<nm:col nm:cname='OMEGA(2,2)'>0.71195872136969895</nm:col>
<nm:col nm:cname='OMEGA(2,3)'>1.0548148602069568E-002</nm:col>
</nm:row>
<nm:row nm:rname='OMEGA(2,4)'>
<nm:col nm:cname='THETA1'>0.0000000000000000</nm:col>
<nm:col nm:cname='THETA2'>0.0000000000000000</nm:col>
<nm:col nm:cname='THETA3'>0.0000000000000000</nm:col>
<nm:col nm:cname='THETA4'>0.0000000000000000</nm:col>
<nm:col nm:cname='THETA5'>0.0000000000000000</nm:col>
<nm:col nm:cname='OMEGA(1,1)'>0.0000000000000000</nm:col>
<nm:col nm:cname='OMEGA(1,2)'>0.0000000000000000</nm:col>
<nm:col nm:cname='OMEGA(1,3)'>0.0000000000000000</nm:col>
<nm:col nm:cname='OMEGA(1,4)'>0.0000000000000000</nm:col>
<nm:col nm:cname='OMEGA(1,5)'>0.0000000000000000</nm:col>
<nm:col nm:cname='OMEGA(2,2)'>0.0000000000000000</nm:col>
<nm:col nm:cname='OMEGA(2,3)'>0.0000000000000000</nm:col>
<nm:col nm:cname='OMEGA(2,4)'>0.0000000000000000</nm:col>
</nm:row>
<nm:row nm:rname='OMEGA(2,5)'>
<nm:col nm:cname='THETA1'>0.0000000000000000</nm:col>
<nm:col nm:cname='THETA2'>0.0000000000000000</nm:col>
<nm:col nm:cname='THETA3'>0.0000000000000000</nm:col>
<nm:col nm:cname='THETA4'>0.0000000000000000</nm:col>
<nm:col nm:cname='THETA5'>0.0000000000000000</nm:col>
<nm:col nm:cname='OMEGA(1,1)'>0.0000000000000000</nm:col>
<nm:col nm:cname='OMEGA(1,2)'>0.0000000000000000</nm:col>
<nm:col nm:cname='OMEGA(1,3)'>0.0000000000000000</nm:col>
<nm:col nm:cname='OMEGA(1,4)'>0.0000000000000000</nm:col>
<nm:col nm:cname='OMEGA(1,5)'>0.0000000000000000</nm:col>
<nm:col nm:cname='OMEGA(2,2)'>0.0000000000000000</nm:col>
<nm:col nm:cname='OMEGA(2,3)'>0.0000000000000000</nm:col>
<nm:col nm:cname='OMEGA(2,4)'>0.0000000000000000</nm:col>
<nm:col nm:cname='OMEGA(2,5)'>0.0000000000000000</nm:col>
</nm:row>
<nm:row nm:rname='OMEGA(3,3)'>
<nm:col nm:cname='THETA1'>-7.0942953002290730E-003</nm:col>
<nm:col nm:cname='THETA2'>9.3242384332267128E-002</nm:col>
<nm:col nm:cname='THETA3'>-0.19199518947766905</nm:col>
<nm:col nm:cname='THETA4'>2.0971651477713880E-002</nm:col>
<nm:col nm:cname='THETA5'>-4.4664523874005858E-002</nm:col>
<nm:col nm:cname='OMEGA(1,1)'>0.10800222057531471</nm:col>
<nm:col nm:cname='OMEGA(1,2)'>0.19305409928739684</nm:col>
<nm:col nm:cname='OMEGA(1,3)'>0.43848197725222837</nm:col>
<nm:col nm:cname='OMEGA(1,4)'>0.0000000000000000</nm:col>
<nm:col nm:cname='OMEGA(1,5)'>0.0000000000000000</nm:col>
<nm:col nm:cname='OMEGA(2,2)'>0.14769398309026396</nm:col>
<nm:col nm:cname='OMEGA(2,3)'>0.55583883094015951</nm:col>
<nm:col nm:cname='OMEGA(2,4)'>0.0000000000000000</nm:col>
<nm:col nm:cname='OMEGA(2,5)'>0.0000000000000000</nm:col>
<nm:col nm:cname='OMEGA(3,3)'>1.9728927759020406E-002</nm:col>
</nm:row>
<nm:row nm:rname='OMEGA(3,4)'>
<nm:col nm:cname='THETA1'>0.0000000000000000</nm:col>
<nm:col nm:cname='THETA2'>0.0000000000000000</nm:col>
<nm:col nm:cname='THETA3'>0.0000000000000000</nm:col>
<nm:col nm:cname='THETA4'>0.0000000000000000</nm:col>
<nm:col nm:cname='THETA5'>0.0000000000000000</nm:col>
<nm:col nm:cname='OMEGA(1,1)'>0.0000000000000000</nm:col>
<nm:col nm:cname='OMEGA(1,2)'>0.0000000000000000</nm:col>
<nm:col nm:cname='OMEGA(1,3)'>0.0000000000000000</nm:col>
<nm:col nm:cname='OMEGA(1,4)'>0.0000000000000000</nm:col>
<nm:col nm:cname='OMEGA(1,5)'>0.0000000000000000</nm:col>
<nm:col nm:cname='OMEGA(2,2)'>0.0000000000000000</nm:col>
<nm:col nm:cname='OMEGA(2,3)'>0.0000000000000000</nm:col>
<nm:col nm:cname='OMEGA(2,4)'>0.0000000000000000</nm:col>
<nm:col nm:cname='OMEGA(2,5)'>0.0000000000000000</nm:col>
<nm:col nm:cname='OMEGA(3,3)'>0.0000000000000000</nm:col>
<nm:col nm:cname='OMEGA(3,4)'>0.0000000000000000</nm:col>
</nm:row>
<nm:row nm:rname='OMEGA(3,5)'>
<nm:col nm:cname='THETA1'>0.0000000000000000</nm:col>
<nm:col nm:cname='THETA2'>0.0000000000000000</nm:col>
<nm:col nm:cname='THETA3'>0.0000000000000000</nm:col>
<nm:col nm:cname='THETA4'>0.0000000000000000</nm:col>
<nm:col nm:cname='THETA5'>0.0000000000000000</nm:col>
<nm:col nm:cname='OMEGA(1,1)'>0.0000000000000000</nm:col>
<nm:col nm:cname='OMEGA(1,2)'>0.0000000000000000</nm:col>
<nm:col nm:cname='OMEGA(1,3)'>0.0000000000000000</nm:col>
<nm:col nm:cname='OMEGA(1,4)'>0.0000000000000000</nm:col>
<nm:col nm:cname='OMEGA(1,5)'>0.0000000000000000</nm:col>
<nm:col nm:cname='OMEGA(2,2)'>0.0000000000000000</nm:col>
<nm:col nm:cname='OMEGA(2,3)'>0.0000000000000000</nm:col>
<nm:col nm:cname='OMEGA(2,4)'>0.0000000000000000</nm:col>
<nm:col nm:cname='OMEGA(2,5)'>0.0000000000000000</nm:col>
<nm:col nm:cname='OMEGA(3,3)'>0.0000000000000000</nm:col>
<nm:col nm:cname='OMEGA(3,4)'>0.0000000000000000</nm:col>
<nm:col nm:cname='OMEGA(3,5)'>0.0000000000000000</nm:col>
</nm:row>
<nm:row nm:rname='OMEGA(4,4)'>
<nm:col nm:cname='THETA1'>0.0000000000000000</nm:col>
<nm:col nm:cname='THETA2'>0.0000000000000000</nm:col>
<nm:col nm:cname='THETA3'>0.0000000000000000</nm:col>
<nm:col nm:cname='THETA4'>0.0000000000000000</nm:col>
<nm:col nm:cname='THETA5'>0.0000000000000000</nm:col>
<nm:col nm:cname='OMEGA(1,1)'>0.0000000000000000</nm:col>
<nm:col nm:cname='OMEGA(1,2)'>0.0000000000000000</nm:col>
<nm:col nm:cname='OMEGA(1,3)'>0.0000000000000000</nm:col>
<nm:col nm:cname='OMEGA(1,4)'>0.0000000000000000</nm:col>
<nm:col nm:cname='OMEGA(1,5)'>0.0000000000000000</nm:col>
<nm:col nm:cname='OMEGA(2,2)'>0.0000000000000000</nm:col>
<nm:col nm:cname='OMEGA(2,3)'>0.0000000000000000</nm:col>
<nm:col nm:cname='OMEGA(2,4)'>0.0000000000000000</nm:col>
<nm:col nm:cname='OMEGA(2,5)'>0.0000000000000000</nm:col>
<nm:col nm:cname='OMEGA(3,3)'>0.0000000000000000</nm:col>
<nm:col nm:cname='OMEGA(3,4)'>0.0000000000000000</nm:col>
<nm:col nm:cname='OMEGA(3,5)'>0.0000000000000000</nm:col>
<nm:col nm:cname='OMEGA(4,4)'>0.0000000000000000</nm:col>
</nm:row>
<nm:row nm:rname='OMEGA(4,5)'>
<nm:col nm:cname='THETA1'>0.0000000000000000</nm:col>
<nm:col nm:cname='THETA2'>0.0000000000000000</nm:col>
<nm:col nm:cname='THETA3'>0.0000000000000000</nm:col>
<nm:col nm:cname='THETA4'>0.0000000000000000</nm:col>
<nm:col nm:cname='THETA5'>0.0000000000000000</nm:col>
<nm:col nm:cname='OMEGA(1,1)'>0.0000000000000000</nm:col>
<nm:col nm:cname='OMEGA(1,2)'>0.0000000000000000</nm:col>
<nm:col nm:cname='OMEGA(1,3)'>0.0000000000000000</nm:col>
<nm:col nm:cname='OMEGA(1,4)'>0.0000000000000000</nm:col>
<nm:col nm:cname='OMEGA(1,5)'>0.0000000000000000</nm:col>
<nm:col nm:cname='OMEGA(2,2)'>0.0000000000000000</nm:col>
<nm:col nm:cname='OMEGA(2,3)'>0.0000000000000000</nm:col>
<nm:col nm:cname='OMEGA(2,4)'>0.0000000000000000</nm:col>
<nm:col nm:cname='OMEGA(2,5)'>0.0000000000000000</nm:col>
<nm:col nm:cname='OMEGA(3,3)'>0.0000000000000000</nm:col>
<nm:col nm:cname='OMEGA(3,4)'>0.0000000000000000</nm:col>
<nm:col nm:cname='OMEGA(3,5)'>0.0000000000000000</nm:col>
<nm:col nm:cname='OMEGA(4,4)'>0.0000000000000000</nm:col>
<nm:col nm:cname='OMEGA(4,5)'>0.0000000000000000</nm:col>
</nm:row>
<nm:row nm:rname='OMEGA(5,5)'>
<nm:col nm:cname='THETA1'>0.0000000000000000</nm:col>
<nm:col nm:cname='THETA2'>0.0000000000000000</nm:col>
<nm:col nm:cname='THETA3'>0.0000000000000000</nm:col>
<nm:col nm:cname='THETA4'>0.0000000000000000</nm:col>
<nm:col nm:cname='THETA5'>0.0000000000000000</nm:col>
<nm:col nm:cname='OMEGA(1,1)'>0.0000000000000000</nm:col>
<nm:col nm:cname='OMEGA(1,2)'>0.0000000000000000</nm:col>
<nm:col nm:cname='OMEGA(1,3)'>0.0000000000000000</nm:col>
<nm:col nm:cname='OMEGA(1,4)'>0.0000000000000000</nm:col>
<nm:col nm:cname='OMEGA(1,5)'>0.0000000000000000</nm:col>
<nm:col nm:cname='OMEGA(2,2)'>0.0000000000000000</nm:col>
<nm:col nm:cname='OMEGA(2,3)'>0.0000000000000000</nm:col>
<nm:col nm:cname='OMEGA(2,4)'>0.0000000000000000</nm:col>
<nm:col nm:cname='OMEGA(2,5)'>0.0000000000000000</nm:col>
<nm:col nm:cname='OMEGA(3,3)'>0.0000000000000000</nm:col>
<nm:col nm:cname='OMEGA(3,4)'>0.0000000000000000</nm:col>
<nm:col nm:cname='OMEGA(3,5)'>0.0000000000000000</nm:col>
<nm:col nm:cname='OMEGA(4,4)'>0.0000000000000000</nm:col>
<nm:col nm:cname='OMEGA(4,5)'>0.0000000000000000</nm:col>
<nm:col nm:cname='OMEGA(5,5)'>0.0000000000000000</nm:col>
</nm:row>
<nm:row nm:rname='SIGMA(1,1)'>
<nm:col nm:cname='THETA1'>7.8993078693619809E-002</nm:col>
<nm:col nm:cname='THETA2'>6.3941642964684506E-002</nm:col>
<nm:col nm:cname='THETA3'>0.16180823940542563</nm:col>
<nm:col nm:cname='THETA4'>7.4232078497226309E-002</nm:col>
<nm:col nm:cname='THETA5'>5.0955147439830208E-003</nm:col>
<nm:col nm:cname='OMEGA(1,1)'>-0.14319001828177783</nm:col>
<nm:col nm:cname='OMEGA(1,2)'>-4.9024077872773172E-002</nm:col>
<nm:col nm:cname='OMEGA(1,3)'>2.5889559139626324E-002</nm:col>
<nm:col nm:cname='OMEGA(1,4)'>0.0000000000000000</nm:col>
<nm:col nm:cname='OMEGA(1,5)'>0.0000000000000000</nm:col>
<nm:col nm:cname='OMEGA(2,2)'>-0.10234591249983364</nm:col>
<nm:col nm:cname='OMEGA(2,3)'>4.0053984160195504E-002</nm:col>
<nm:col nm:cname='OMEGA(2,4)'>0.0000000000000000</nm:col>
<nm:col nm:cname='OMEGA(2,5)'>0.0000000000000000</nm:col>
<nm:col nm:cname='OMEGA(3,3)'>0.12525326175133153</nm:col>
<nm:col nm:cname='OMEGA(3,4)'>0.0000000000000000</nm:col>
<nm:col nm:cname='OMEGA(3,5)'>0.0000000000000000</nm:col>
<nm:col nm:cname='OMEGA(4,4)'>0.0000000000000000</nm:col>
<nm:col nm:cname='OMEGA(4,5)'>0.0000000000000000</nm:col>
<nm:col nm:cname='OMEGA(5,5)'>0.0000000000000000</nm:col>
<nm:col nm:cname='SIGMA(1,1)'>1.2259517179966292E-003</nm:col>
</nm:row>
</nm:correlation>
<nm:invcovariance>
<nm:row nm:rname='THETA1'>
<nm:col nm:cname='THETA1'>549.72420842577651</nm:col>
</nm:row>
<nm:row nm:rname='THETA2'>
<nm:col nm:cname='THETA1'>-396.00794752714199</nm:col>
<nm:col nm:cname='THETA2'>2980.5539502080160</nm:col>
</nm:row>
<nm:row nm:rname='THETA3'>
<nm:col nm:cname='THETA1'>-221.04687224377113</nm:col>
<nm:col nm:cname='THETA2'>-1178.7935898422729</nm:col>
<nm:col nm:cname='THETA3'>1898.3236050510768</nm:col>
</nm:row>
<nm:row nm:rname='THETA4'>
<nm:col nm:cname='THETA1'>213.40309068567745</nm:col>
<nm:col nm:cname='THETA2'>267.09337806695771</nm:col>
<nm:col nm:cname='THETA3'>-343.49767699682906</nm:col>
<nm:col nm:cname='THETA4'>3047.6724289243125</nm:col>
</nm:row>
<nm:row nm:rname='THETA5'>
<nm:col nm:cname='THETA1'>281.71142886407927</nm:col>
<nm:col nm:cname='THETA2'>447.66204040486241</nm:col>
<nm:col nm:cname='THETA3'>-204.79783567503770</nm:col>
<nm:col nm:cname='THETA4'>-105.90962239980369</nm:col>
<nm:col nm:cname='THETA5'>1269.4051302828934</nm:col>
</nm:row>
<nm:row nm:rname='OMEGA(1,1)'>
<nm:col nm:cname='THETA1'>-109.02199021044312</nm:col>
<nm:col nm:cname='THETA2'>68.646792118238494</nm:col>
<nm:col nm:cname='THETA3'>124.90509990416506</nm:col>
<nm:col nm:cname='THETA4'>-198.35920710959476</nm:col>
<nm:col nm:cname='THETA5'>81.710945433880141</nm:col>
<nm:col nm:cname='OMEGA(1,1)'>1265.6974562153753</nm:col>
</nm:row>
<nm:row nm:rname='OMEGA(1,2)'>
<nm:col nm:cname='THETA1'>-67.689108407417564</nm:col>
<nm:col nm:cname='THETA2'>274.06720330354563</nm:col>
<nm:col nm:cname='THETA3'>-278.51333273907358</nm:col>
<nm:col nm:cname='THETA4'>150.58285600104236</nm:col>
<nm:col nm:cname='THETA5'>-402.55104652031980</nm:col>
<nm:col nm:cname='OMEGA(1,1)'>-1553.6708778722991</nm:col>
<nm:col nm:cname='OMEGA(1,2)'>10186.137557973907</nm:col>
</nm:row>
<nm:row nm:rname='OMEGA(1,3)'>
<nm:col nm:cname='THETA1'>-140.23481492787573</nm:col>
<nm:col nm:cname='THETA2'>-232.57608978830112</nm:col>
<nm:col nm:cname='THETA3'>128.49285170390004</nm:col>
<nm:col nm:cname='THETA4'>501.16255146081591</nm:col>
<nm:col nm:cname='THETA5'>-119.73863963702883</nm:col>
<nm:col nm:cname='OMEGA(1,1)'>-1926.2713643607492</nm:col>
<nm:col nm:cname='OMEGA(1,2)'>-379.90338794989952</nm:col>
<nm:col nm:cname='OMEGA(1,3)'>7162.6512095855569</nm:col>
</nm:row>
<nm:row nm:rname='OMEGA(1,4)'>
<nm:col nm:cname='THETA1'>0.0000000000000000</nm:col>
<nm:col nm:cname='THETA2'>0.0000000000000000</nm:col>
<nm:col nm:cname='THETA3'>0.0000000000000000</nm:col>
<nm:col nm:cname='THETA4'>0.0000000000000000</nm:col>
<nm:col nm:cname='THETA5'>0.0000000000000000</nm:col>
<nm:col nm:cname='OMEGA(1,1)'>0.0000000000000000</nm:col>
<nm:col nm:cname='OMEGA(1,2)'>0.0000000000000000</nm:col>
<nm:col nm:cname='OMEGA(1,3)'>0.0000000000000000</nm:col>
<nm:col nm:cname='OMEGA(1,4)'>0.0000000000000000</nm:col>
</nm:row>
<nm:row nm:rname='OMEGA(1,5)'>
<nm:col nm:cname='THETA1'>0.0000000000000000</nm:col>
<nm:col nm:cname='THETA2'>0.0000000000000000</nm:col>
<nm:col nm:cname='THETA3'>0.0000000000000000</nm:col>
<nm:col nm:cname='THETA4'>0.0000000000000000</nm:col>
<nm:col nm:cname='THETA5'>0.0000000000000000</nm:col>
<nm:col nm:cname='OMEGA(1,1)'>0.0000000000000000</nm:col>
<nm:col nm:cname='OMEGA(1,2)'>0.0000000000000000</nm:col>
<nm:col nm:cname='OMEGA(1,3)'>0.0000000000000000</nm:col>
<nm:col nm:cname='OMEGA(1,4)'>0.0000000000000000</nm:col>
<nm:col nm:cname='OMEGA(1,5)'>0.0000000000000000</nm:col>
</nm:row>
<nm:row nm:rname='OMEGA(2,2)'>
<nm:col nm:cname='THETA1'>175.18640034186666</nm:col>
<nm:col nm:cname='THETA2'>-1261.6179958061266</nm:col>
<nm:col nm:cname='THETA3'>1205.6688996861139</nm:col>
<nm:col nm:cname='THETA4'>568.61913489288986</nm:col>
<nm:col nm:cname='THETA5'>-394.44822361932620</nm:col>
<nm:col nm:cname='OMEGA(1,1)'>578.41636079039847</nm:col>
<nm:col nm:cname='OMEGA(1,2)'>-7653.4648762987399</nm:col>
<nm:col nm:cname='OMEGA(1,3)'>748.49716387540275</nm:col>
<nm:col nm:cname='OMEGA(1,4)'>0.0000000000000000</nm:col>
<nm:col nm:cname='OMEGA(1,5)'>0.0000000000000000</nm:col>
<nm:col nm:cname='OMEGA(2,2)'>33618.192132030112</nm:col>
</nm:row>
<nm:row nm:rname='OMEGA(2,3)'>
<nm:col nm:cname='THETA1'>-132.21433115981563</nm:col>
<nm:col nm:cname='THETA2'>2235.9002324777971</nm:col>
<nm:col nm:cname='THETA3'>-2641.8025028572556</nm:col>
<nm:col nm:cname='THETA4'>-496.14996300656594</nm:col>
<nm:col nm:cname='THETA5'>-214.20154173092601</nm:col>
<nm:col nm:cname='OMEGA(1,1)'>1605.1853484458161</nm:col>
<nm:col nm:cname='OMEGA(1,2)'>-5190.1141335248085</nm:col>
<nm:col nm:cname='OMEGA(1,3)'>-4670.0137444025349</nm:col>
<nm:col nm:cname='OMEGA(1,4)'>0.0000000000000000</nm:col>
<nm:col nm:cname='OMEGA(1,5)'>0.0000000000000000</nm:col>
<nm:col nm:cname='OMEGA(2,2)'>-19534.758678759528</nm:col>
<nm:col nm:cname='OMEGA(2,3)'>43165.883848580961</nm:col>
</nm:row>
<nm:row nm:rname='OMEGA(2,4)'>
<nm:col nm:cname='THETA1'>0.0000000000000000</nm:col>
<nm:col nm:cname='THETA2'>0.0000000000000000</nm:col>
<nm:col nm:cname='THETA3'>0.0000000000000000</nm:col>
<nm:col nm:cname='THETA4'>0.0000000000000000</nm:col>
<nm:col nm:cname='THETA5'>0.0000000000000000</nm:col>
<nm:col nm:cname='OMEGA(1,1)'>0.0000000000000000</nm:col>
<nm:col nm:cname='OMEGA(1,2)'>0.0000000000000000</nm:col>
<nm:col nm:cname='OMEGA(1,3)'>0.0000000000000000</nm:col>
<nm:col nm:cname='OMEGA(1,4)'>0.0000000000000000</nm:col>
<nm:col nm:cname='OMEGA(1,5)'>0.0000000000000000</nm:col>
<nm:col nm:cname='OMEGA(2,2)'>0.0000000000000000</nm:col>
<nm:col nm:cname='OMEGA(2,3)'>0.0000000000000000</nm:col>
<nm:col nm:cname='OMEGA(2,4)'>0.0000000000000000</nm:col>
</nm:row>
<nm:row nm:rname='OMEGA(2,5)'>
<nm:col nm:cname='THETA1'>0.0000000000000000</nm:col>
<nm:col nm:cname='THETA2'>0.0000000000000000</nm:col>
<nm:col nm:cname='THETA3'>0.0000000000000000</nm:col>
<nm:col nm:cname='THETA4'>0.0000000000000000</nm:col>
<nm:col nm:cname='THETA5'>0.0000000000000000</nm:col>
<nm:col nm:cname='OMEGA(1,1)'>0.0000000000000000</nm:col>
<nm:col nm:cname='OMEGA(1,2)'>0.0000000000000000</nm:col>
<nm:col nm:cname='OMEGA(1,3)'>0.0000000000000000</nm:col>
<nm:col nm:cname='OMEGA(1,4)'>0.0000000000000000</nm:col>
<nm:col nm:cname='OMEGA(1,5)'>0.0000000000000000</nm:col>
<nm:col nm:cname='OMEGA(2,2)'>0.0000000000000000</nm:col>
<nm:col nm:cname='OMEGA(2,3)'>0.0000000000000000</nm:col>
<nm:col nm:cname='OMEGA(2,4)'>0.0000000000000000</nm:col>
<nm:col nm:cname='OMEGA(2,5)'>0.0000000000000000</nm:col>
</nm:row>
<nm:row nm:rname='OMEGA(3,3)'>
<nm:col nm:cname='THETA1'>170.48822382573923</nm:col>
<nm:col nm:cname='THETA2'>-1295.7796832163262</nm:col>
<nm:col nm:cname='THETA3'>1438.0748403019663</nm:col>
<nm:col nm:cname='THETA4'>-313.35295968988623</nm:col>
<nm:col nm:cname='THETA5'>207.59027442278136</nm:col>
<nm:col nm:cname='OMEGA(1,1)'>413.92622682881097</nm:col>
<nm:col nm:cname='OMEGA(1,2)'>651.40795520909978</nm:col>
<nm:col nm:cname='OMEGA(1,3)'>-1659.5759000994776</nm:col>
<nm:col nm:cname='OMEGA(1,4)'>0.0000000000000000</nm:col>
<nm:col nm:cname='OMEGA(1,5)'>0.0000000000000000</nm:col>
<nm:col nm:cname='OMEGA(2,2)'>4643.4083584774035</nm:col>
<nm:col nm:cname='OMEGA(2,3)'>-9587.2777125922785</nm:col>
<nm:col nm:cname='OMEGA(2,4)'>0.0000000000000000</nm:col>
<nm:col nm:cname='OMEGA(2,5)'>0.0000000000000000</nm:col>
<nm:col nm:cname='OMEGA(3,3)'>6406.8094076565430</nm:col>
</nm:row>
<nm:row nm:rname='OMEGA(3,4)'>
<nm:col nm:cname='THETA1'>0.0000000000000000</nm:col>
<nm:col nm:cname='THETA2'>0.0000000000000000</nm:col>
<nm:col nm:cname='THETA3'>0.0000000000000000</nm:col>
<nm:col nm:cname='THETA4'>0.0000000000000000</nm:col>
<nm:col nm:cname='THETA5'>0.0000000000000000</nm:col>
<nm:col nm:cname='OMEGA(1,1)'>0.0000000000000000</nm:col>
<nm:col nm:cname='OMEGA(1,2)'>0.0000000000000000</nm:col>
<nm:col nm:cname='OMEGA(1,3)'>0.0000000000000000</nm:col>
<nm:col nm:cname='OMEGA(1,4)'>0.0000000000000000</nm:col>
<nm:col nm:cname='OMEGA(1,5)'>0.0000000000000000</nm:col>
<nm:col nm:cname='OMEGA(2,2)'>0.0000000000000000</nm:col>
<nm:col nm:cname='OMEGA(2,3)'>0.0000000000000000</nm:col>
<nm:col nm:cname='OMEGA(2,4)'>0.0000000000000000</nm:col>
<nm:col nm:cname='OMEGA(2,5)'>0.0000000000000000</nm:col>
<nm:col nm:cname='OMEGA(3,3)'>0.0000000000000000</nm:col>
<nm:col nm:cname='OMEGA(3,4)'>0.0000000000000000</nm:col>
</nm:row>
<nm:row nm:rname='OMEGA(3,5)'>
<nm:col nm:cname='THETA1'>0.0000000000000000</nm:col>
<nm:col nm:cname='THETA2'>0.0000000000000000</nm:col>
<nm:col nm:cname='THETA3'>0.0000000000000000</nm:col>
<nm:col nm:cname='THETA4'>0.0000000000000000</nm:col>
<nm:col nm:cname='THETA5'>0.0000000000000000</nm:col>
<nm:col nm:cname='OMEGA(1,1)'>0.0000000000000000</nm:col>
<nm:col nm:cname='OMEGA(1,2)'>0.0000000000000000</nm:col>
<nm:col nm:cname='OMEGA(1,3)'>0.0000000000000000</nm:col>
<nm:col nm:cname='OMEGA(1,4)'>0.0000000000000000</nm:col>
<nm:col nm:cname='OMEGA(1,5)'>0.0000000000000000</nm:col>
<nm:col nm:cname='OMEGA(2,2)'>0.0000000000000000</nm:col>
<nm:col nm:cname='OMEGA(2,3)'>0.0000000000000000</nm:col>
<nm:col nm:cname='OMEGA(2,4)'>0.0000000000000000</nm:col>
<nm:col nm:cname='OMEGA(2,5)'>0.0000000000000000</nm:col>
<nm:col nm:cname='OMEGA(3,3)'>0.0000000000000000</nm:col>
<nm:col nm:cname='OMEGA(3,4)'>0.0000000000000000</nm:col>
<nm:col nm:cname='OMEGA(3,5)'>0.0000000000000000</nm:col>
</nm:row>
<nm:row nm:rname='OMEGA(4,4)'>
<nm:col nm:cname='THETA1'>0.0000000000000000</nm:col>
<nm:col nm:cname='THETA2'>0.0000000000000000</nm:col>
<nm:col nm:cname='THETA3'>0.0000000000000000</nm:col>
<nm:col nm:cname='THETA4'>0.0000000000000000</nm:col>
<nm:col nm:cname='THETA5'>0.0000000000000000</nm:col>
<nm:col nm:cname='OMEGA(1,1)'>0.0000000000000000</nm:col>
<nm:col nm:cname='OMEGA(1,2)'>0.0000000000000000</nm:col>
<nm:col nm:cname='OMEGA(1,3)'>0.0000000000000000</nm:col>
<nm:col nm:cname='OMEGA(1,4)'>0.0000000000000000</nm:col>
<nm:col nm:cname='OMEGA(1,5)'>0.0000000000000000</nm:col>
<nm:col nm:cname='OMEGA(2,2)'>0.0000000000000000</nm:col>
<nm:col nm:cname='OMEGA(2,3)'>0.0000000000000000</nm:col>
<nm:col nm:cname='OMEGA(2,4)'>0.0000000000000000</nm:col>
<nm:col nm:cname='OMEGA(2,5)'>0.0000000000000000</nm:col>
<nm:col nm:cname='OMEGA(3,3)'>0.0000000000000000</nm:col>
<nm:col nm:cname='OMEGA(3,4)'>0.0000000000000000</nm:col>
<nm:col nm:cname='OMEGA(3,5)'>0.0000000000000000</nm:col>
<nm:col nm:cname='OMEGA(4,4)'>0.0000000000000000</nm:col>
</nm:row>
<nm:row nm:rname='OMEGA(4,5)'>
<nm:col nm:cname='THETA1'>0.0000000000000000</nm:col>
<nm:col nm:cname='THETA2'>0.0000000000000000</nm:col>
<nm:col nm:cname='THETA3'>0.0000000000000000</nm:col>
<nm:col nm:cname='THETA4'>0.0000000000000000</nm:col>
<nm:col nm:cname='THETA5'>0.0000000000000000</nm:col>
<nm:col nm:cname='OMEGA(1,1)'>0.0000000000000000</nm:col>
<nm:col nm:cname='OMEGA(1,2)'>0.0000000000000000</nm:col>
<nm:col nm:cname='OMEGA(1,3)'>0.0000000000000000</nm:col>
<nm:col nm:cname='OMEGA(1,4)'>0.0000000000000000</nm:col>
<nm:col nm:cname='OMEGA(1,5)'>0.0000000000000000</nm:col>
<nm:col nm:cname='OMEGA(2,2)'>0.0000000000000000</nm:col>
<nm:col nm:cname='OMEGA(2,3)'>0.0000000000000000</nm:col>
<nm:col nm:cname='OMEGA(2,4)'>0.0000000000000000</nm:col>
<nm:col nm:cname='OMEGA(2,5)'>0.0000000000000000</nm:col>
<nm:col nm:cname='OMEGA(3,3)'>0.0000000000000000</nm:col>
<nm:col nm:cname='OMEGA(3,4)'>0.0000000000000000</nm:col>
<nm:col nm:cname='OMEGA(3,5)'>0.0000000000000000</nm:col>
<nm:col nm:cname='OMEGA(4,4)'>0.0000000000000000</nm:col>
<nm:col nm:cname='OMEGA(4,5)'>0.0000000000000000</nm:col>
</nm:row>
<nm:row nm:rname='OMEGA(5,5)'>
<nm:col nm:cname='THETA1'>0.0000000000000000</nm:col>
<nm:col nm:cname='THETA2'>0.0000000000000000</nm:col>
<nm:col nm:cname='THETA3'>0.0000000000000000</nm:col>
<nm:col nm:cname='THETA4'>0.0000000000000000</nm:col>
<nm:col nm:cname='THETA5'>0.0000000000000000</nm:col>
<nm:col nm:cname='OMEGA(1,1)'>0.0000000000000000</nm:col>
<nm:col nm:cname='OMEGA(1,2)'>0.0000000000000000</nm:col>
<nm:col nm:cname='OMEGA(1,3)'>0.0000000000000000</nm:col>
<nm:col nm:cname='OMEGA(1,4)'>0.0000000000000000</nm:col>
<nm:col nm:cname='OMEGA(1,5)'>0.0000000000000000</nm:col>
<nm:col nm:cname='OMEGA(2,2)'>0.0000000000000000</nm:col>
<nm:col nm:cname='OMEGA(2,3)'>0.0000000000000000</nm:col>
<nm:col nm:cname='OMEGA(2,4)'>0.0000000000000000</nm:col>
<nm:col nm:cname='OMEGA(2,5)'>0.0000000000000000</nm:col>
<nm:col nm:cname='OMEGA(3,3)'>0.0000000000000000</nm:col>
<nm:col nm:cname='OMEGA(3,4)'>0.0000000000000000</nm:col>
<nm:col nm:cname='OMEGA(3,5)'>0.0000000000000000</nm:col>
<nm:col nm:cname='OMEGA(4,4)'>0.0000000000000000</nm:col>
<nm:col nm:cname='OMEGA(4,5)'>0.0000000000000000</nm:col>
<nm:col nm:cname='OMEGA(5,5)'>0.0000000000000000</nm:col>
</nm:row>
<nm:row nm:rname='SIGMA(1,1)'>
<nm:col nm:cname='THETA1'>-1801.5149582654878</nm:col>
<nm:col nm:cname='THETA2'>3608.7127837602452</nm:col>
<nm:col nm:cname='THETA3'>-5718.1071503964631</nm:col>
<nm:col nm:cname='THETA4'>-3384.5821403144487</nm:col>
<nm:col nm:cname='THETA5'>-1386.1592978748222</nm:col>
<nm:col nm:cname='OMEGA(1,1)'>6658.7661042243599</nm:col>
<nm:col nm:cname='OMEGA(1,2)'>-6125.5191364026068</nm:col>
<nm:col nm:cname='OMEGA(1,3)'>-10442.626089372628</nm:col>
<nm:col nm:cname='OMEGA(1,4)'>0.0000000000000000</nm:col>
<nm:col nm:cname='OMEGA(1,5)'>0.0000000000000000</nm:col>
<nm:col nm:cname='OMEGA(2,2)'>17321.769404459283</nm:col>
<nm:col nm:cname='OMEGA(2,3)'>5918.1919341768235</nm:col>
<nm:col nm:cname='OMEGA(2,4)'>0.0000000000000000</nm:col>
<nm:col nm:cname='OMEGA(2,5)'>0.0000000000000000</nm:col>
<nm:col nm:cname='OMEGA(3,3)'>-6616.6989115073247</nm:col>
<nm:col nm:cname='OMEGA(3,4)'>0.0000000000000000</nm:col>
<nm:col nm:cname='OMEGA(3,5)'>0.0000000000000000</nm:col>
<nm:col nm:cname='OMEGA(4,4)'>0.0000000000000000</nm:col>
<nm:col nm:cname='OMEGA(4,5)'>0.0000000000000000</nm:col>
<nm:col nm:cname='OMEGA(5,5)'>0.0000000000000000</nm:col>
<nm:col nm:cname='SIGMA(1,1)'>763414.66927880724</nm:col>
</nm:row>
</nm:invcovariance>
<nm:eigenvalues>
<nm:val nm:name='1'>0.12163883028115452</nm:val>
<nm:val nm:name='2'>0.14440793615611422</nm:val>
<nm:val nm:name='3'>0.20316803899040109</nm:val>
<nm:val nm:name='4'>0.32878061211761467</nm:val>
<nm:val nm:name='5'>0.33925733941044328</nm:val>
<nm:val nm:name='6'>0.54280631118632228</nm:val>
<nm:val nm:name='7'>0.82659959505810177</nm:val>
<nm:val nm:name='8'>0.89903090848769374</nm:val>
<nm:val nm:name='9'>1.2126469356103859</nm:val>
<nm:val nm:name='10'>1.2858521089253547</nm:val>
<nm:val nm:name='11'>2.4681172195690451</nm:val>
<nm:val nm:name='12'>3.6276941642073695</nm:val>
</nm:eigenvalues>
</nm:estimation>
<nm:post_process_times>
<nm:post_elapsed_time>2.94</nm:post_elapsed_time>
<nm:finaloutput_elapsed_time>0.14</nm:finaloutput_elapsed_time>
</nm:post_process_times>
</nm:problem>
</nm:nonmem>
<nm:stop_datetime>2023-11-24T16:46:04.108</nm:stop_datetime>
<nm:total_cputime>35.246</nm:total_cputime>
</nm:output>
